mcpimageprocessing/1.jpg
mcpimageprocessing/__init__.py
mcpimageprocessing/main.py
mcpimageprocessing/test.py
mcpimageprocessing-0.1.1.dist-info/METADATA
mcpimageprocessing-0.1.1.dist-info/WHEEL
mcpimageprocessing-0.1.1.dist-info/entry_points.txt
mcpimageprocessing-0.1.1.dist-info/RECORD
